odoo/addons/ssi_partner_public_offering/README.rst
odoo/addons/ssi_partner_public_offering/__init__.py
odoo/addons/ssi_partner_public_offering/__manifest__.py
odoo/addons/ssi_partner_public_offering/models/__init__.py
odoo/addons/ssi_partner_public_offering/models/company_public_offering_type.py
odoo/addons/ssi_partner_public_offering/models/res_partner.py
odoo/addons/ssi_partner_public_offering/security/ir.model.access.csv
odoo/addons/ssi_partner_public_offering/security/res_group_data.xml
odoo/addons/ssi_partner_public_offering/static/description/icon.png
odoo/addons/ssi_partner_public_offering/views/company_public_offering_type_views.xml
odoo/addons/ssi_partner_public_offering/views/res_partner_views.xml
odoo14_addon_ssi_partner_public_offering-14.0.1.0.0.dist-info/METADATA
odoo14_addon_ssi_partner_public_offering-14.0.1.0.0.dist-info/WHEEL
odoo14_addon_ssi_partner_public_offering-14.0.1.0.0.dist-info/top_level.txt
odoo14_addon_ssi_partner_public_offering-14.0.1.0.0.dist-info/RECORD
